llegos/__init__.py
llegos/abc/cognitive/reinforcement.py
llegos/logger.py
llegos/research.py
llegos-0.1.0.dist-info/LICENSE
llegos-0.1.0.dist-info/METADATA
llegos-0.1.0.dist-info/WHEEL
llegos-0.1.0.dist-info/RECORD
