Metadata-Version: 2.1
Name: llegos
Version: 0.1.0
Summary: Where we explore the future of multi-agent systems
License: LGPLv3
Author: Cyrus Nouroozi,
Author-email: cyrus@edendaolab.com
Requires-Python: >=3.10,<=3.12
Classifier: License :: Other/Proprietary License
Classifier: Programming Language :: Python :: 3
Classifier: Programming Language :: Python :: 3.10
Classifier: Programming Language :: Python :: 3.11
Classifier: Programming Language :: Python :: 3.12
Requires-Dist: beartype (>=0.15.0,<0.16.0)
Requires-Dist: deepmerge (>=1.1.0,<2.0.0)
Requires-Dist: match-ref (>=1.0.1,<2.0.0)
Requires-Dist: more-itertools (>=10.2.0,<11.0.0)
Requires-Dist: networkx (>=3.2,<4.0)
Requires-Dist: pydantic (>=2.0,<3.0)
Requires-Dist: pydash (>=7.0.6,<8.0.0)
Requires-Dist: pyee (>=11.1.0,<12.0.0)
Requires-Dist: python-statemachine (>=2.1.2,<3.0.0)
Requires-Dist: sorcery (>=0.2.2,<0.3.0)
Requires-Dist: svix-ksuid (>=0.6.2,<0.7.0)
